src/__init__.py
src/resize_image.py
torch_resize_images-0.1.7.data/scripts/torch-resize
torch_resize_images-0.1.7.dist-info/LICENSE
torch_resize_images-0.1.7.dist-info/METADATA
torch_resize_images-0.1.7.dist-info/WHEEL
torch_resize_images-0.1.7.dist-info/top_level.txt
torch_resize_images-0.1.7.dist-info/RECORD
