Metadata-Version: 2.1
Name: torch-resize-images
Version: 0.1.7
Summary: A Python library to resize images using PyTorch
Home-page: https://github.com/NilsHendrikLukas/torch-resize-images
Author: Nils Lukas
Author-email: nlukas@uwaterloo.ca
License: MIT
Keywords: resize image pytorch
Platform: UNKNOWN
Requires-Dist: Pillow
Requires-Dist: torch
Requires-Dist: torchvision
Requires-Dist: tqdm
